aqueductus/__init__.py
aqueductus/__main__.py
aqueductus/providers.py
aqueductus/reporters.py
aqueductus/runner.py
aqueductus/testers.py
aqueductus/utils.py
aqueductus-1.1.0.dist-info/LICENSE
aqueductus-1.1.0.dist-info/METADATA
aqueductus-1.1.0.dist-info/WHEEL
aqueductus-1.1.0.dist-info/entry_points.txt
aqueductus-1.1.0.dist-info/RECORD
