Metadata-Version: 2.3
Name: aqueductus
Version: 1.1.0
Summary: A data testing framework that executes queries on configurable data providers and validates the results with customizable YAML-defined assertions.
License: Apache-2.0
Author: Remo Yukoff
Author-email: remo.yukoff@gmail.com
Requires-Python: >=3.12,<4.0.0
Classifier: License :: OSI Approved :: Apache Software License
Classifier: Programming Language :: Python :: 3
Classifier: Programming Language :: Python :: 3.12
Classifier: Programming Language :: Python :: 3.13
Provides-Extra: athena
Provides-Extra: mysql
Provides-Extra: postgresql
Requires-Dist: click (>=8.1.8,<9.0.0)
Requires-Dist: psycopg2-binary (>=2.9.10,<3.0.0) ; extra == "postgresql"
Requires-Dist: pyathena (>=3.12.2,<4.0.0) ; extra == "athena"
Requires-Dist: pymysql (>=1.1.1,<2.0.0) ; extra == "mysql"
Requires-Dist: pyyaml (>=6.0.2,<7.0.0)
